pyxpcm/__init__.py
pyxpcm/io.py
pyxpcm/models.py
pyxpcm/plot.py
pyxpcm/stat.py
pyxpcm/tutorial.py
pyxpcm/utils.py
pyxpcm/xarray.py
pyxpcm/tests/__init__.py
pyxpcm/tests/test_doc.py
pyxpcm/tests/test_fit.py
pyxpcm/tests/test_io.py
pyxpcm/tests/test_pcm.py
pyxpcm/tests/test_stats.py
pyxpcm-0.4.1.dist-info/LICENSE.txt
pyxpcm-0.4.1.dist-info/METADATA
pyxpcm-0.4.1.dist-info/WHEEL
pyxpcm-0.4.1.dist-info/top_level.txt
pyxpcm-0.4.1.dist-info/RECORD
