Metadata-Version: 2.1
Name: pyxpcm
Version: 0.4.1
Summary: pyxpcm: Ocean Profile Classification Model
Home-page: http://github.com/obidam/pyxpcm
Author: Guillaume Maze
Author-email: gmaze@ifremer.fr
License: GPLv3
Platform: UNKNOWN
Classifier: Programming Language :: Python :: 3.6
Classifier: License :: OSI Approved :: GNU General Public License v3 (GPLv3)
Classifier: Operating System :: OS Independent
Classifier: Intended Audience :: Science/Research
Requires-Dist: scipy (>=1.1.0)
Requires-Dist: xarray (>=0.12.1)
Requires-Dist: scikit-learn (>=0.21)
Requires-Dist: ipython (>=5.0.0)
Requires-Dist: numpydoc (>=0.6.0)
Requires-Dist: netCDF4 (>=1.3.1)
Requires-Dist: dask (>=0.16.0)
Requires-Dist: toolz (>=0.8.2)
